main/__init__.py
main/helper/creditionals.py
main/helper/pdf.py
main/helper/spinner.py
main/helper/store_vectors.py
main/helper/web_crawl.py
talem_ai_cli-0.1.3.dist-info/METADATA
talem_ai_cli-0.1.3.dist-info/WHEEL
talem_ai_cli-0.1.3.dist-info/entry_points.txt
talem_ai_cli-0.1.3.dist-info/top_level.txt
talem_ai_cli-0.1.3.dist-info/RECORD
