Metadata-Version: 2.1
Name: talem-ai-cli
Version: 0.1.3
Summary: Administrative tool for RAG apps
Home-page: https://github.com/hemit99123/talem-ai-cli
Author: Hemit Patel
Author-email: hemitvpatel@gmail.com
License: MIT
Classifier: Development Status :: 3 - Alpha
Classifier: Intended Audience :: Developers
Classifier: Topic :: Software Development :: Build Tools
Classifier: License :: OSI Approved :: MIT License
Classifier: Programming Language :: Python :: 3.8
Classifier: Programming Language :: Python :: 3.9
Classifier: Programming Language :: Python :: 3.10
Requires-Python: >=3.8
Requires-Dist: click
Requires-Dist: aiofiles
Requires-Dist: PyPDF2
Requires-Dist: pypdf
Requires-Dist: pyfiglet
Requires-Dist: langchain
Requires-Dist: langchain-community
Requires-Dist: langchain-astradb
Requires-Dist: langchain-huggingface
Requires-Dist: bs4
Requires-Dist: reportlab
